ufm_config_diff/__init__.py
ufm_config_diff/config_diff.py
ufm_config_diff/docker_operations.py
ufm_config_diff-1.0.4.dist-info/LICENSE
ufm_config_diff-1.0.4.dist-info/METADATA
ufm_config_diff-1.0.4.dist-info/WHEEL
ufm_config_diff-1.0.4.dist-info/entry_points.txt
ufm_config_diff-1.0.4.dist-info/top_level.txt
ufm_config_diff-1.0.4.dist-info/RECORD
