Metadata-Version: 2.1
Name: ufm-config-diff
Version: 1.0.4
Summary: Production-ready UFM configuration comparison tool with automated email reports, interactive HTML tables, and CI/CD support via --yes flag
Home-page: https://github.com/Mellanox/ufm-config-diff
Author: NVIDIA
Author-email: support@nvidia.com
Project-URL: Bug Reports, https://github.com/Mellanox/ufm-config-diff/issues
Project-URL: Source, https://github.com/Mellanox/ufm-config-diff
Project-URL: Documentation, https://github.com/Mellanox/ufm-config-diff/blob/master/README.md
Keywords: ufm nvidia mellanox infiniband docker configuration comparison networking
Classifier: Development Status :: 5 - Production/Stable
Classifier: Intended Audience :: System Administrators
Classifier: Intended Audience :: Developers
Classifier: License :: OSI Approved :: MIT License
Classifier: Programming Language :: Python :: 3
Classifier: Programming Language :: Python :: 3.6
Classifier: Programming Language :: Python :: 3.7
Classifier: Programming Language :: Python :: 3.8
Classifier: Programming Language :: Python :: 3.9
Classifier: Programming Language :: Python :: 3.10
Classifier: Programming Language :: Python :: 3.11
Classifier: Topic :: System :: Systems Administration
Classifier: Topic :: System :: Networking
Classifier: Topic :: Software Development :: Testing
Classifier: Operating System :: POSIX :: Linux
Requires-Python: >=3.6
License-File: LICENSE
Requires-Dist: beautifulsoup4
Requires-Dist: colorama
Requires-Dist: paramiko
